[
  {
    "id": 1,
    "codigo": "1",
    "nombre": "UNIVERSIDAD GABRIELA MISTRAL",
    "tipo": "Universidades",
    "acreditacion": "3 anos",
    "region_id": null,
    "region": null,
    "created_at": "2025-02-25T04:35:32.66762+00:00"
  },
  {
    "id": 2,
    "codigo": "2",
    "nombre": "UNIVERSIDAD FINIS TERRAE",
    "tipo": "Universidades",
    "acreditacion": "5 anos",
    "region_id": null,
    "region": null,
    "created_at": "2025-02-25T04:35:32.66762+00:00"
  },
  {
    "id": 3,
    "codigo": "3",
    "nombre": "UNIVERSIDAD DIEGO PORTALES",
    "tipo": "Universidades",
    "acreditacion": "6 anos",
    "region_id": null,
    "region": null,
    "created_at": "2025-02-25T04:35:32.66762+00:00"
  },
  {
    "id": 4,
    "codigo": "4",
    "nombre": "UNIVERSIDAD CENTRAL DE CHILE",
    "tipo": "Universidades",
    "acreditacion": "5 anos",
    "region_id": null,
    "region": null,
    "created_at": "2025-02-25T04:35:32.66762+00:00"
  },
  {
    "id": 6,
    "codigo": "9",
    "nombre": "UNIVERSIDAD DEL ALBA",
    "tipo": "Universidades",
    "acreditacion": "3 anos",
    "region_id": null,
    "region": null,
    "created_at": "2025-02-25T04:35:32.66762+00:00"
  },
  {
    "id": 7,
    "codigo": "10",
    "nombre": "UNIVERSIDAD MAYOR",
    "tipo": "Universidades",
    "acreditacion": "5 anos",
    "region_id": null,
    "region": null,
    "created_at": "2025-02-25T04:35:32.66762+00:00"
  },
  {
    "id": 8,
    "codigo": "11",
    "nombre": "UNIVERSIDAD ACADEMIA DE HUMANISMO CRISTIANO",
    "tipo": "Universidades",
    "acreditacion": "4 anos",
    "region_id": null,
    "region": null,
    "created_at": "2025-02-25T04:35:32.66762+00:00"
  },
  {
    "id": 9,
    "codigo": "13",
    "nombre": "UNIVERSIDAD SANTO TOMAS",
    "tipo": "Universidades",
    "acreditacion": "4 anos",
    "region_id": null,
    "region": null,
    "created_at": "2025-02-25T04:35:32.66762+00:00"
  },
  {
    "id": 11,
    "codigo": "17",
    "nombre": "UNIVERSIDAD SEK",
    "tipo": "Universidades",
    "acreditacion": "3 anos",
    "region_id": null,
    "region": null,
    "created_at": "2025-02-25T04:35:32.66762+00:00"
  },
  {
    "id": 12,
    "codigo": "19",
    "nombre": "UNIVERSIDAD DE LAS AMERICAS",
    "tipo": "Universidades",
    "acreditacion": "5 anos",
    "region_id": null,
    "region": null,
    "created_at": "2025-02-25T04:35:32.66762+00:00"
  }
]